{"LE1yr8YaJcdaRNyeRix9cQ==":"mbr-2000x1333.jpg","H1e5kQbdmH0VKcY1OMfl8A==":"mbr-1-2000x1333.jpg","MsA6+lSsrBYz0q22tCJ/WA==":"mbr-2000x1330.jpg","wKj0GqABZxTFjGRJoijv5w==":"mbr-600x400.jpg","gHXIC27O2F5w4w2AusYJpg==":"mbr-600x480.jpg","4ocy3sMm+oiPDaIYZtLJIw==":"mbr-600x600.jpg","MFKSmWDwe88qi+6NtoxhWQ==":"mbr-1-600x400.jpg","g8t/qAOC7w+4K70iDhJf8g==":"mbr-2-600x400.jpg","p3IGkwP8tLOsjTrFxyupyg==":"mbr-3-600x400.jpg","aP6pEBCULwVuf6rUZd6foQ==":"mbr-4-600x400.jpg","W2XgwgfVXEMWDqO5+emaEw==":"mbr-5-600x400.jpg","YKSJieB6afbvGLCETSpsnA==":"mbr-6-600x400.jpg","GZSDtz6RbVOrsce8m5iVFg==":"mbr-600x398.jpg","F8tUEQCGENZkgfHEONONTQ==":"dr_braun_site-600x414.jpg","+mjS52luMemJaBSg7iDQ2w==":"mbr-7-600x400.jpg","YqnclyN8MTD3pUKAlJ/yPQ==":"mbr-8-600x400.jpg","heSgQkkyqcpj11CQEoWQYg==":"mbr-600x446.jpg","R51gYkfl0UoNN7nQKU2+zg==":"wecker2-600x600.jpg","7cX4f0GNgSnKt1QvPFrmNw==":"mbr-9-600x400.jpg","8BB/ZSQBYTccGWq0MPvA1w==":"fotolia_109838181_m-600x399.jpg","kKKFv+2Dh7hJRuABuN5l1Q==":"fotolia-600x600.jpg","DBEhHsvYfxEBn1ReRsqUHQ==":"cimg4375-600x600.jpg","ixFMgBeVdPShuhOrp3XV/Q==":"cimg4375a-600x600.jpg","qV8TKPDJ/TnHO6OEk+cP9g==":"mbr-2000x2451.jpg","MpKl770I6qeooY7BTdFx+g==":"mbr-2-2000x1333.jpg","5RwXBfS0eYl984fu9fdtXw==":"man-working-on-imac-600x400.jpg","pnkn55C4vr+ENrlzs++1bg==":"ipad-pro-with-notes-600x399.jpg","MePsasVskwFviH+KicruzQ==":"holding-iphone-6s-on-a-train-station-600x400.jpg"}